oscfar/README.md
oscfar/__init__.py
oscfar/cfar.py
oscfar/cluster.py
oscfar/filters.py
oscfar/gaussian_fit.py
oscfar/reload.py
oscfar/utils.py
oscfar-1.1.18.dist-info/licenses/LICENSE
oscfar-1.1.18.dist-info/METADATA
oscfar-1.1.18.dist-info/WHEEL
oscfar-1.1.18.dist-info/top_level.txt
oscfar-1.1.18.dist-info/RECORD
