Metadata-Version: 2.4
Name: oscfar
Version: 1.1.18
Summary: Order Statistic Constant False Alarm Rate detector package
Author: Chloé Legué
Author-email: chloe.legue@mail.mcgill.ca
Requires-Python: >=3.8
License-File: LICENSE
Requires-Dist: numpy
Requires-Dist: scipy
Requires-Dist: matplotlib
Requires-Dist: pandas
Requires-Dist: scikit-learn
Requires-Dist: statsmodels
Requires-Dist: uncertainties
Dynamic: author
Dynamic: author-email
Dynamic: description
Dynamic: description-content-type
Dynamic: license-file
Dynamic: requires-dist
Dynamic: requires-python
Dynamic: summary
